DESCRIPTION
MANIFEST.in
VERSION.txt
requirements.txt
setup.py
git_projects/__init__.py
git_projects/command.py
git_projects/config.py
git_projects/console.py
git_projects/gp.py
git_projects/shortcut.py
git_projects.egg-info/PKG-INFO
git_projects.egg-info/SOURCES.txt
git_projects.egg-info/dependency_links.txt
git_projects.egg-info/entry_points.txt
git_projects.egg-info/requires.txt
git_projects.egg-info/top_level.txt