Metadata-Version: 1.0
Name: git-projects
Version: 0.3.3
Summary: Pure git commands for multi-repository projects
Home-page: https://github.com/thavel/git-projects
Author: Thibaut Havel
Author-email: UNKNOWN
License: UNKNOWN
Platform: UNKNOWN
